linkml_model/README.md
linkml_model/__init__.py
linkml_model/annotations.py
linkml_model/array.py
linkml_model/datasets.py
linkml_model/excel/meta.xlsx
linkml_model/extensions.py
linkml_model/graphql/README.md
linkml_model/graphql/meta.graphql
linkml_model/json/README.md
linkml_model/json/annotations.json
linkml_model/json/datasets.json
linkml_model/json/extensions.json
linkml_model/json/mappings.json
linkml_model/json/meta.json
linkml_model/json/types.json
linkml_model/json/units.json
linkml_model/json/validation.json
linkml_model/jsonld/README.md
linkml_model/jsonld/annotations.context.jsonld
linkml_model/jsonld/annotations.model.context.jsonld
linkml_model/jsonld/context.jsonld
linkml_model/jsonld/datasets.context.jsonld
linkml_model/jsonld/datasets.model.context.jsonld
linkml_model/jsonld/extensions.context.jsonld
linkml_model/jsonld/extensions.model.context.jsonld
linkml_model/jsonld/mappings.context.jsonld
linkml_model/jsonld/mappings.model.context.jsonld
linkml_model/jsonld/meta.context.jsonld
linkml_model/jsonld/meta.jsonld
linkml_model/jsonld/meta.model.context.jsonld
linkml_model/jsonld/types.context.jsonld
linkml_model/jsonld/types.model.context.jsonld
linkml_model/jsonld/units.context.jsonld
linkml_model/jsonld/units.model.context.jsonld
linkml_model/jsonld/validation.context.jsonld
linkml_model/jsonld/validation.model.context.jsonld
linkml_model/jsonschema/README.md
linkml_model/jsonschema/annotations.schema.json
linkml_model/jsonschema/datasets.schema.json
linkml_model/jsonschema/extensions.schema.json
linkml_model/jsonschema/mappings.schema.json
linkml_model/jsonschema/meta.schema.json
linkml_model/jsonschema/types.schema.json
linkml_model/jsonschema/units.schema.json
linkml_model/jsonschema/validation.schema.json
linkml_model/linkml_files.py
linkml_model/mappings.py
linkml_model/meta.py
linkml_model/model/README.md
linkml_model/model/docs/credits.md
linkml_model/model/docs/home.md
linkml_model/model/docs/specification/00preamble.md
linkml_model-1.8.0.dist-info/METADATA
linkml_model-1.8.0.dist-info/WHEEL
linkml_model-1.8.0.dist-info/RECORD
