Metadata-Version: 2.1
Name: linkml-model
Version: 1.8.0
Summary: Metamodel schema, documentation, and specification for the Linked Open Data Modeling Language (LinkML)
Home-page: https://linkml.io/
License: MIT
Keywords: linked data,linkml,metamodel
Author: Chris Mungall
Author-email: cjmungall@lbl.gov
Requires-Python: >=3.9,<4.0
Classifier: Development Status :: 5 - Production/Stable
Classifier: Environment :: Console
Classifier: Intended Audience :: Developers
Classifier: Intended Audience :: Healthcare Industry
Classifier: Intended Audience :: Science/Research
Classifier: License :: CC0 1.0 Universal (CC0 1.0) Public Domain Dedication
Classifier: License :: OSI Approved :: MIT License
Classifier: Programming Language :: Python :: 3
Classifier: Programming Language :: Python :: 3.9
Classifier: Programming Language :: Python :: 3.10
Classifier: Programming Language :: Python :: 3.11
Classifier: Programming Language :: Python :: 3.12
Classifier: Topic :: Software Development :: Libraries :: Python Modules
Requires-Dist: linkml-runtime (>=1.6.3,<2.0.0)
Project-URL: Documentation, https://linkml.io/linkml-model/docs/
Project-URL: Repository, https://github.com/linkml/linkml-model/
